result_parser_agent/__init__.py
result_parser_agent/exceptions.py
result_parser_agent/main.py
result_parser_agent/cli/__init__.py
result_parser_agent/cli/app.py
result_parser_agent/cli/commands/__init__.py
result_parser_agent/cli/commands/cache.py
result_parser_agent/cli/commands/parse.py
result_parser_agent/cli/commands/registry.py
result_parser_agent/config/__init__.py
result_parser_agent/config/settings.py
result_parser_agent/models/schema.py
result_parser_agent/services/__init__.py
result_parser_agent/services/base.py
result_parser_agent/services/cache_service.py
result_parser_agent/services/parsing_service.py
result_parser_agent/services/registry_service.py
result_parser_agent/services/workload_service.py
result_parser_agent/utils/downloader.py
result_parser_agent/utils/validators.py
result_parser_agent-2.0.3.dist-info/METADATA
result_parser_agent-2.0.3.dist-info/WHEEL
result_parser_agent-2.0.3.dist-info/entry_points.txt
result_parser_agent-2.0.3.dist-info/licenses/LICENSE
result_parser_agent-2.0.3.dist-info/RECORD
