Metadata-Version: 2.4
Name: result-parser-agent
Version: 2.0.3
Summary: A CLI tool for extracting metrics from raw result files using workload-specific tools
Project-URL: Homepage, https://github.com/Infobellit-Solutions-Pvt-Ltd/result-parser-agent
Project-URL: Repository, https://github.com/Infobellit-Solutions-Pvt-Ltd/result-parser-agent
Project-URL: Documentation, https://github.com/Infobellit-Solutions-Pvt-Ltd/result-parser-agent#readme
Project-URL: Issues, https://github.com/Infobellit-Solutions-Pvt-Ltd/result-parser-agent/issues
Author-email: Akhilreddy <akhil@Infobellit.com>
License: MIT
License-File: LICENSE
Keywords: agent,ai,langgraph,metrics,parsing
Classifier: Development Status :: 3 - Alpha
Classifier: Intended Audience :: Developers
Classifier: License :: OSI Approved :: MIT License
Classifier: Programming Language :: Python :: 3
Classifier: Programming Language :: Python :: 3.11
Classifier: Programming Language :: Python :: 3.12
Classifier: Topic :: Scientific/Engineering :: Artificial Intelligence
Classifier: Topic :: Software Development :: Libraries :: Python Modules
Requires-Python: <3.13,>=3.11
Requires-Dist: click>=8.0.0
Requires-Dist: loguru>=0.7.0
Requires-Dist: pydantic-settings>=2.0.0
Requires-Dist: pydantic>=2.0.0
Requires-Dist: pytest-asyncio>=1.1.0
Requires-Dist: pytest-cov>=6.2.1
Requires-Dist: pytest>=8.4.1
Requires-Dist: python-dotenv>=1.1.1
Requires-Dist: pyyaml>=6.0.0
Requires-Dist: typer>=0.9.0
Provides-Extra: dev
Requires-Dist: bandit>=1.7.0; extra == 'dev'
Requires-Dist: black>=24.0.0; extra == 'dev'
Requires-Dist: build>=1.0.0; extra == 'dev'
Requires-Dist: isort>=5.13.0; extra == 'dev'
Requires-Dist: mypy>=1.8.0; extra == 'dev'
Requires-Dist: ruff>=0.3.0; extra == 'dev'
Requires-Dist: twine>=4.0.0; extra == 'dev'
